sarcasticase.py
sarcasticase-0.1.0.dist-info/entry_points.txt
sarcasticase-0.1.0.dist-info/LICENSE
sarcasticase-0.1.0.dist-info/WHEEL
sarcasticase-0.1.0.dist-info/METADATA
sarcasticase-0.1.0.dist-info/RECORD
