Metadata-Version: 2.1
Name: sarcasticase
Version: 0.1.0
Summary: Easily convert text to be like sarcastic Spongebob
Home-page: https://github.com/smithk86/sarcasticase/
License: MIT
Author: Kyle Smith
Author-email: smithk86@gmail.com
Requires-Python: >=3.0,<4.0
Classifier: License :: OSI Approved :: MIT License
Classifier: Programming Language :: Python :: 3
Classifier: Programming Language :: Python :: 3.10
Classifier: Programming Language :: Python :: 3.4
Classifier: Programming Language :: Python :: 3.5
Classifier: Programming Language :: Python :: 3.6
Classifier: Programming Language :: Python :: 3.7
Classifier: Programming Language :: Python :: 3.8
Classifier: Programming Language :: Python :: 3.9
Project-URL: Repository, https://github.com/smithk86/sarcasticase/
